streamlit_calendar/__init__.py
streamlit_calendar/frontend/.env
streamlit_calendar/frontend/.prettierrc
streamlit_calendar/frontend/package-lock.json
streamlit_calendar/frontend/package.json
streamlit_calendar/frontend/public/bootstrap.min.css
streamlit_calendar/frontend/public/index.html
streamlit_calendar/frontend/src/components/Calendar.tsx
streamlit_calendar/frontend/src/index.tsx
streamlit_calendar/frontend/src/react-app-env.d.ts
streamlit_calendar/frontend/src/styles/Calendar.css
streamlit_calendar/frontend/src/types/Calendar.type.ts
streamlit_calendar/frontend/tsconfig.json
streamlit_calendar-1.3.0.dist-info/LICENSE
streamlit_calendar-1.3.0.dist-info/METADATA
streamlit_calendar-1.3.0.dist-info/WHEEL
streamlit_calendar-1.3.0.dist-info/RECORD
