Metadata-Version: 2.3
Name: streamlit-calendar
Version: 1.3.0
Summary: 📆 A Streamlit component to show callendar using FullCalendar (https://fullcalendar.io)
License: Apache-2.0
Keywords: streamlit,streamlit-component
Author: Muhammad Luqman
Author-email: im.imperativa@gmail.com
Requires-Python: >=3.10,<4.0
Classifier: License :: OSI Approved :: Apache Software License
Classifier: Programming Language :: Python :: 3
Classifier: Programming Language :: Python :: 3.10
Classifier: Programming Language :: Python :: 3.11
Classifier: Programming Language :: Python :: 3.12
Classifier: Programming Language :: Python :: 3.13
Requires-Dist: streamlit (>=1.42.0,<2.0.0)
Project-URL: Repository, https://github.com/im-perativa/streamlit-calendar
